aiogram_middlewares/__init__.py
aiogram_middlewares/rater/__init__.py
aiogram_middlewares/rater/base.py
aiogram_middlewares/rater/caches/__init__.py
aiogram_middlewares/rater/caches/lazy_ttl.py
aiogram_middlewares/rater/extensions/__init__.py
aiogram_middlewares/rater/extensions/debouncing.py
aiogram_middlewares/rater/extensions/notify.py
aiogram_middlewares/rater/extensions/serializable.py
aiogram_middlewares/rater/extensions/throttling/__init__.py
aiogram_middlewares/rater/extensions/throttling/extensions/__init__.py
aiogram_middlewares/rater/extensions/throttling/extensions/notify.py
aiogram_middlewares/rater/extensions/throttling/locks.py
aiogram_middlewares/rater/extensions/throttling/throttling.py
aiogram_middlewares/rater/filters.py
aiogram_middlewares/rater/middlewares.py
aiogram_middlewares/rater/models.py
aiogram_middlewares/rater/rater.py
aiogram_middlewares/rater/types.py
aiogram_middlewares/utils.py
aiogram_middlewares-0.0.3.dist-info/LICENSE
aiogram_middlewares-0.0.3.dist-info/METADATA
aiogram_middlewares-0.0.3.dist-info/WHEEL
aiogram_middlewares-0.0.3.dist-info/RECORD
